{
  "comision": "Futuro, Ciencias, Tecnología, Conocimiento e Innovación",
  "prmID": "3303",
  "integrantes": [
    {
      "nombre": "Sr. Eric Aedo Jeldres",
      "url_ficha": "https://www.camara.cl/diputados/detalle/mociones.aspx?prmID=1097"
    },
    {
      "nombre": "Sra. Marta Bravo Salinas",
      "url_ficha": "https://www.camara.cl/diputados/detalle/mociones.aspx?prmID=1113"
    },
    {
      "nombre": "Sr. Johannes Kaiser Barents-Von Hohenhagen",
      "url_ficha": "https://www.camara.cl/diputados/detalle/mociones.aspx?prmID=1135"
    },
    {
      "nombre": "Sra. Paula Labra Besserer",
      "url_ficha": "https://www.camara.cl/diputados/detalle/mociones.aspx?prmID=1136"
    },
    {
      "nombre": "Sr. Tomás Lagomarsino Guzmán",
      "url_ficha": "https://www.camara.cl/diputados/detalle/mociones.aspx?prmID=1137"
    },
    {
      "nombre": "Sr. Daniel Lilayu Vivanco",
      "url_ficha": "https://www.camara.cl/diputados/detalle/mociones.aspx?prmID=1140"
    },
    {
      "nombre": "Sra. Helia Molina Milman",
      "url_ficha": "https://www.camara.cl/diputados/detalle/mociones.aspx?prmID=1147"
    },
    {
      "nombre": "Sra. Erika Olivera De La Fuente",
      "url_ficha": "https://www.camara.cl/diputados/detalle/mociones.aspx?prmID=1057"
    },
    {
      "nombre": "Sr. Rubén Darío Oyarzo Figueroa",
      "url_ficha": "https://www.camara.cl/diputados/detalle/mociones.aspx?prmID=1155"
    },
    {
      "nombre": "Sr. Hernán Palma Pérez",
      "url_ficha": "https://www.camara.cl/diputados/detalle/mociones.aspx?prmID=1156"
    },
    {
      "nombre": "Sra. Marcela Riquelme Aliaga",
      "url_ficha": "https://www.camara.cl/diputados/detalle/mociones.aspx?prmID=1164"
    },
    {
      "nombre": "Sr. Gaspar Rivas Sánchez",
      "url_ficha": "https://www.camara.cl/diputados/detalle/mociones.aspx?prmID=948"
    },
    {
      "nombre": "Sra. Gael Yeomans Araya",
      "url_ficha": "https://www.camara.cl/diputados/detalle/mociones.aspx?prmID=1087"
    }
  ]
}